[
    {
        "id": "sessions",
        "name": "Sessions",
        "options": [
            {
                "id": "accessible-facility",
                "name": "Facility and area is accessible to participants"
            },
            {
                "id": "assistive-listening-devices",
                "name": "<a href=\"https://www.w3.org/WAI/teach-advocate/accessible-presentations/#ald\">Assistive listening devices</a> (ALD), <a href=\"https://www.w3.org/WAI/teach-advocate/accessible-presentations/#terps\">interpreters</a>, and <a href=\"https://www.w3.org/WAI/teach-advocate/accessible-presentations/#captions\">captioners</a>, provided as needed"
            },
            {
                "id": "caption-audio",
                "name": "<a href=\"https://www.w3.org/WAI/media/av/captions/\">Captions</a> and/or <a href=\"https://www.w3.org/WAI/media/av/transcripts/\">transcripts</a> for audio provided"
            },
            {
                "id": "description-of-visual-information",
                "name": "<a href=\"https://www.w3.org/WAI/media/av/description/\">Description of visual information</a> - integrated description, audio description, or text description"
            },        
            {
                "id": "pre-check-available",
                "name": "Pre-session technology check, provided as needed - dedicated time to participants set up any relevant technology, or additional settings"
            }
        ]
    },
    {
        "id": "material-and-media",
        "name": "Material and Media",
        "options": [
            {
                "id": "accessible-format-handouts",
                "name": "Handouts, slides, and other material in accessible formats"
            },
            {
                "id": "accessible-electronic-handout",
                "name": "Handouts, slides, and other electronic material is accessible - all content meet <a href=\"https://www.w3.org/WAI/standards-guidelines/wcag/\">WCAG</a>, at least Level AA"
            },
            {
                "id": "material-ahead-of-time",
                "name": "Material provided ahead of time, provided as needed"
            },
            {
                "id": "media-accessible",
                "name": "Media fully accessible — including audio and video used in sessions, and recordings of sessions provided afterwards (see <a href=\"https://www.w3.org/WAI/media/av/\">Making Audio and Video Media Accessible</a>)"
            }
        ]
    }
]

